gym_cooking/__init__.py
gym_cooking/cooking_book/__init__.py
gym_cooking/cooking_book/recipe.py
gym_cooking/cooking_book/recipe_drawer.py
gym_cooking/cooking_world/__init__.py
gym_cooking/cooking_world/abstract_classes.py
gym_cooking/cooking_world/constants.py
gym_cooking/cooking_world/cooking_world.py
gym_cooking/cooking_world/world_objects.py
gym_cooking/environment/__init__.py
gym_cooking/environment/cooking_zoo.py
gym_cooking/environment/environment.py
gym_cooking/environment/game/__init__.py
gym_cooking/environment/game/game.py
gym_cooking/environment/game/graphic_pipeline.py
gym_cooking/environment/graphics/__init__.py
gym_cooking/environment/graphics/graphic_store.py
gym_cooking/misc/__init__.py
gym_cooking/misc/game/__init__.py
gym_cooking/misc/game/utils.py
gym_cooking/misc/game/graphics/ChoppedCarrot.png
gym_cooking/misc/game/graphics/ChoppedLettuce-ChoppedOnion-ChoppedTomato.png
gym_cooking/misc/game/graphics/ChoppedLettuce-ChoppedOnion.png
gym_cooking/misc/game/graphics/ChoppedLettuce-ChoppedTomato.png
gym_cooking/misc/game/graphics/ChoppedLettuce.png
gym_cooking/misc/game/graphics/ChoppedOnion-ChoppedTomato.png
gym_cooking/misc/game/graphics/ChoppedOnion.png
gym_cooking/misc/game/graphics/ChoppedTomato.png
gym_cooking/misc/game/graphics/FreshCarrot.png
gym_cooking/misc/game/graphics/FreshLettuce.png
gym_cooking/misc/game/graphics/FreshOnion.png
gym_cooking/misc/game/graphics/FreshTomato.png
gym_cooking/misc/game/graphics/InProgressCarrot.png
gym_cooking/misc/game/graphics/MashedCarrot.png
gym_cooking/misc/game/graphics/Plate.png
gym_cooking/misc/game/graphics/__init__.py
gym_cooking/misc/game/graphics/agent-blue.png
gym_cooking/misc/game/graphics/agent-green.png
gym_cooking/misc/game/graphics/agent-magenta.png
gym_cooking/misc/game/graphics/agent-yellow.png
gym_cooking/misc/game/graphics/arrow_down.png
gym_cooking/misc/game/graphics/arrow_left.png
gym_cooking/misc/game/graphics/arrow_right.png
gym_cooking/misc/game/graphics/arrow_up.png
gym_cooking_lipo-0.0.2.dist-info/LICENSE
gym_cooking_lipo-0.0.2.dist-info/METADATA
gym_cooking_lipo-0.0.2.dist-info/WHEEL
gym_cooking_lipo-0.0.2.dist-info/top_level.txt
gym_cooking_lipo-0.0.2.dist-info/RECORD
