Metadata-Version: 2.1
Name: gym-cooking-lipo
Version: 0.0.2
Summary: A variant of https://github.com/DavidRother/cooking_zoo used in LIPO
License-File: LICENSE
Requires-Dist: gym ==0.18.3
Requires-Dist: numpy >=1.21.2
Requires-Dist: pygame ==2.0.1
Requires-Dist: PettingZoo ==1.9.0
